{
  "schemaVersion": "1.0.0",
  "replayId": "replay_009",
  "entities": [
    {
      "schemaVersion": "1.0.0",
      "replayId": "replay_009",
      "entityKey": "controller:1556492",
      "entityIndex": 1556492,
      "serial": null,
      "handle": null,
      "classId": null,
      "className": null,
      "classification": "player_controller",
      "playerKey": "76561199629896135",
      "team": 2,
      "firstSeenTick": 320,
      "lastSeenTick": 138925,
      "independentValidation": {
        "categoryStatus": "not_required",
        "sampled": false,
        "visible": false,
        "identityStatus": "not_required",
        "timingStatus": "not_required",
        "comparisonIds": [],
        "limitations": []
      }
    },
    {
      "schemaVersion": "1.0.0",
      "replayId": "replay_009",
      "entityKey": "pawn:3899472",
      "entityIndex": 3899472,
      "serial": null,
      "handle": null,
      "classId": null,
      "className": null,
      "classification": "player_pawn",
      "playerKey": "76561199629896135",
      "team": 2,
      "firstSeenTick": 320,
      "lastSeenTick": 138925,
      "independentValidation": {
        "categoryStatus": "not_required",
        "sampled": false,
        "visible": false,
        "identityStatus": "not_required",
        "timingStatus": "not_required",
        "comparisonIds": [],
        "limitations": []
      }
    },
    {
      "schemaVersion": "1.0.0",
      "replayId": "replay_009",
      "entityKey": "controller:13811722",
      "entityIndex": 13811722,
      "serial": null,
      "handle": null,
      "classId": null,
      "className": null,
      "classification": "player_controller",
      "playerKey": "76561198333532769",
      "team": 2,
      "firstSeenTick": 320,
      "lastSeenTick": 138925,
      "independentValidation": {
        "categoryStatus": "not_required",
        "sampled": false,
        "visible": false,
        "identityStatus": "not_required",
        "timingStatus": "not_required",
        "comparisonIds": [],
        "limitations": []
      }
    },
    {
      "schemaVersion": "1.0.0",
      "replayId": "replay_009",
      "entityKey": "pawn:10272846",
      "entityIndex": 10272846,
      "serial": null,
      "handle": null,
      "classId": null,
      "className": null,
      "classification": "player_pawn",
      "playerKey": "76561198333532769",
      "team": 2,
      "firstSeenTick": 320,
      "lastSeenTick": 138925,
      "independentValidation": {
        "categoryStatus": "not_required",
        "sampled": false,
        "visible": false,
        "identityStatus": "not_required",
        "timingStatus": "not_required",
        "comparisonIds": [],
        "limitations": []
      }
    },
    {
      "schemaVersion": "1.0.0",
      "replayId": "replay_009",
      "entityKey": "controller:12615683",
      "entityIndex": 12615683,
      "serial": null,
      "handle": null,
      "classId": null,
      "className": null,
      "classification": "player_controller",
      "playerKey": "76561198853073718",
      "team": 2,
      "firstSeenTick": 320,
      "lastSeenTick": 138925,
      "independentValidation": {
        "categoryStatus": "not_required",
        "sampled": false,
        "visible": false,
        "identityStatus": "not_required",
        "timingStatus": "not_required",
        "comparisonIds": [],
        "limitations": []
      }
    },
    {
      "schemaVersion": "1.0.0",
      "replayId": "replay_009",
      "entityKey": "pawn:4472924",
      "entityIndex": 4472924,
      "serial": null,
      "handle": null,
      "classId": null,
      "className": null,
      "classification": "player_pawn",
      "playerKey": "76561198853073718",
      "team": 2,
      "firstSeenTick": 320,
      "lastSeenTick": 138925,
      "independentValidation": {
        "categoryStatus": "not_required",
        "sampled": false,
        "visible": false,
        "identityStatus": "not_required",
        "timingStatus": "not_required",
        "comparisonIds": [],
        "limitations": []
      }
    },
    {
      "schemaVersion": "1.0.0",
      "replayId": "replay_009",
      "entityKey": "controller:14942217",
      "entityIndex": 14942217,
      "serial": null,
      "handle": null,
      "classId": null,
      "className": null,
      "classification": "player_controller",
      "playerKey": "76561198810406708",
      "team": 2,
      "firstSeenTick": 320,
      "lastSeenTick": 138925,
      "independentValidation": {
        "categoryStatus": "not_required",
        "sampled": false,
        "visible": false,
        "identityStatus": "not_required",
        "timingStatus": "not_required",
        "comparisonIds": [],
        "limitations": []
      }
    },
    {
      "schemaVersion": "1.0.0",
      "replayId": "replay_009",
      "entityKey": "pawn:11042898",
      "entityIndex": 11042898,
      "serial": null,
      "handle": null,
      "classId": null,
      "className": null,
      "classification": "player_pawn",
      "playerKey": "76561198810406708",
      "team": 2,
      "firstSeenTick": 320,
      "lastSeenTick": 138925,
      "independentValidation": {
        "categoryStatus": "not_required",
        "sampled": false,
        "visible": false,
        "identityStatus": "not_required",
        "timingStatus": "not_required",
        "comparisonIds": [],
        "limitations": []
      }
    },
    {
      "schemaVersion": "1.0.0",
      "replayId": "replay_009",
      "entityKey": "controller:13713410",
      "entityIndex": 13713410,
      "serial": null,
      "handle": null,
      "classId": null,
      "className": null,
      "classification": "player_controller",
      "playerKey": "76561198835717166",
      "team": 2,
      "firstSeenTick": 320,
      "lastSeenTick": 138925,
      "independentValidation": {
        "categoryStatus": "not_required",
        "sampled": false,
        "visible": false,
        "identityStatus": "not_required",
        "timingStatus": "not_required",
        "comparisonIds": [],
        "limitations": []
      }
    },
    {
      "schemaVersion": "1.0.0",
      "replayId": "replay_009",
      "entityKey": "pawn:2015315",
      "entityIndex": 2015315,
      "serial": null,
      "handle": null,
      "classId": null,
      "className": null,
      "classification": "player_pawn",
      "playerKey": "76561198835717166",
      "team": 2,
      "firstSeenTick": 320,
      "lastSeenTick": 138925,
      "independentValidation": {
        "categoryStatus": "not_required",
        "sampled": false,
        "visible": false,
        "identityStatus": "not_required",
        "timingStatus": "not_required",
        "comparisonIds": [],
        "limitations": []
      }
    },
    {
      "schemaVersion": "1.0.0",
      "replayId": "replay_009",
      "entityKey": "controller:4669453",
      "entityIndex": 4669453,
      "serial": null,
      "handle": null,
      "classId": null,
      "className": null,
      "classification": "player_controller",
      "playerKey": "76561199550367846",
      "team": 2,
      "firstSeenTick": 320,
      "lastSeenTick": 138925,
      "independentValidation": {
        "categoryStatus": "not_required",
        "sampled": false,
        "visible": false,
        "identityStatus": "not_required",
        "timingStatus": "not_required",
        "comparisonIds": [],
        "limitations": []
      }
    },
    {
      "schemaVersion": "1.0.0",
      "replayId": "replay_009",
      "entityKey": "pawn:7979104",
      "entityIndex": 7979104,
      "serial": null,
      "handle": null,
      "classId": null,
      "className": null,
      "classification": "player_pawn",
      "playerKey": "76561199550367846",
      "team": 2,
      "firstSeenTick": 320,
      "lastSeenTick": 138925,
      "independentValidation": {
        "categoryStatus": "not_required",
        "sampled": false,
        "visible": false,
        "identityStatus": "not_required",
        "timingStatus": "not_required",
        "comparisonIds": [],
        "limitations": []
      }
    },
    {
      "schemaVersion": "1.0.0",
      "replayId": "replay_009",
      "entityKey": "controller:13680645",
      "entityIndex": 13680645,
      "serial": null,
      "handle": null,
      "classId": null,
      "className": null,
      "classification": "player_controller",
      "playerKey": "76561198277999856",
      "team": 3,
      "firstSeenTick": 320,
      "lastSeenTick": 138925,
      "independentValidation": {
        "categoryStatus": "not_required",
        "sampled": false,
        "visible": false,
        "identityStatus": "not_required",
        "timingStatus": "not_required",
        "comparisonIds": [],
        "limitations": []
      }
    },
    {
      "schemaVersion": "1.0.0",
      "replayId": "replay_009",
      "entityKey": "pawn:12517455",
      "entityIndex": 12517455,
      "serial": null,
      "handle": null,
      "classId": null,
      "className": null,
      "classification": "player_pawn",
      "playerKey": "76561198277999856",
      "team": 3,
      "firstSeenTick": 320,
      "lastSeenTick": 138925,
      "independentValidation": {
        "categoryStatus": "not_required",
        "sampled": false,
        "visible": false,
        "identityStatus": "not_required",
        "timingStatus": "not_required",
        "comparisonIds": [],
        "limitations": []
      }
    },
    {
      "schemaVersion": "1.0.0",
      "replayId": "replay_009",
      "entityKey": "controller:8896516",
      "entityIndex": 8896516,
      "serial": null,
      "handle": null,
      "classId": null,
      "className": null,
      "classification": "player_controller",
      "playerKey": "76561199143692579",
      "team": 3,
      "firstSeenTick": 320,
      "lastSeenTick": 138925,
      "independentValidation": {
        "categoryStatus": "not_required",
        "sampled": false,
        "visible": false,
        "identityStatus": "not_required",
        "timingStatus": "not_required",
        "comparisonIds": [],
        "limitations": []
      }
    },
    {
      "schemaVersion": "1.0.0",
      "replayId": "replay_009",
      "entityKey": "pawn:16269406",
      "entityIndex": 16269406,
      "serial": null,
      "handle": null,
      "classId": null,
      "className": null,
      "classification": "player_pawn",
      "playerKey": "76561199143692579",
      "team": 3,
      "firstSeenTick": 320,
      "lastSeenTick": 138925,
      "independentValidation": {
        "categoryStatus": "not_required",
        "sampled": false,
        "visible": false,
        "identityStatus": "not_required",
        "timingStatus": "not_required",
        "comparisonIds": [],
        "limitations": []
      }
    },
    {
      "schemaVersion": "1.0.0",
      "replayId": "replay_009",
      "entityKey": "controller:12353542",
      "entityIndex": 12353542,
      "serial": null,
      "handle": null,
      "classId": null,
      "className": null,
      "classification": "player_controller",
      "playerKey": "76561198824019977",
      "team": 3,
      "firstSeenTick": 320,
      "lastSeenTick": 138925,
      "independentValidation": {
        "categoryStatus": "not_required",
        "sampled": false,
        "visible": false,
        "identityStatus": "not_required",
        "timingStatus": "not_required",
        "comparisonIds": [],
        "limitations": []
      }
    },
    {
      "schemaVersion": "1.0.0",
      "replayId": "replay_009",
      "entityKey": "pawn:11796564",
      "entityIndex": 11796564,
      "serial": null,
      "handle": null,
      "classId": null,
      "className": null,
      "classification": "player_pawn",
      "playerKey": "76561198824019977",
      "team": 3,
      "firstSeenTick": 320,
      "lastSeenTick": 138925,
      "independentValidation": {
        "categoryStatus": "not_required",
        "sampled": false,
        "visible": false,
        "identityStatus": "not_required",
        "timingStatus": "not_required",
        "comparisonIds": [],
        "limitations": []
      }
    },
    {
      "schemaVersion": "1.0.0",
      "replayId": "replay_009",
      "entityKey": "controller:7520263",
      "entityIndex": 7520263,
      "serial": null,
      "handle": null,
      "classId": null,
      "className": null,
      "classification": "player_controller",
      "playerKey": "76561198144455377",
      "team": 3,
      "firstSeenTick": 320,
      "lastSeenTick": 138925,
      "independentValidation": {
        "categoryStatus": "not_required",
        "sampled": false,
        "visible": false,
        "identityStatus": "not_required",
        "timingStatus": "not_required",
        "comparisonIds": [],
        "limitations": []
      }
    },
    {
      "schemaVersion": "1.0.0",
      "replayId": "replay_009",
      "entityKey": "pawn:12992599",
      "entityIndex": 12992599,
      "serial": null,
      "handle": null,
      "classId": null,
      "className": null,
      "classification": "player_pawn",
      "playerKey": "76561198144455377",
      "team": 3,
      "firstSeenTick": 320,
      "lastSeenTick": 138925,
      "independentValidation": {
        "categoryStatus": "not_required",
        "sampled": false,
        "visible": false,
        "identityStatus": "not_required",
        "timingStatus": "not_required",
        "comparisonIds": [],
        "limitations": []
      }
    },
    {
      "schemaVersion": "1.0.0",
      "replayId": "replay_009",
      "entityKey": "controller:10862600",
      "entityIndex": 10862600,
      "serial": null,
      "handle": null,
      "classId": null,
      "className": null,
      "classification": "player_controller",
      "playerKey": "76561198057452710",
      "team": 3,
      "firstSeenTick": 320,
      "lastSeenTick": 138925,
      "independentValidation": {
        "categoryStatus": "not_required",
        "sampled": false,
        "visible": false,
        "identityStatus": "not_required",
        "timingStatus": "not_required",
        "comparisonIds": [],
        "limitations": []
      }
    },
    {
      "schemaVersion": "1.0.0",
      "replayId": "replay_009",
      "entityKey": "pawn:14565453",
      "entityIndex": 14565453,
      "serial": null,
      "handle": null,
      "classId": null,
      "className": null,
      "classification": "player_pawn",
      "playerKey": "76561198057452710",
      "team": 3,
      "firstSeenTick": 320,
      "lastSeenTick": 138925,
      "independentValidation": {
        "categoryStatus": "not_required",
        "sampled": false,
        "visible": false,
        "identityStatus": "not_required",
        "timingStatus": "not_required",
        "comparisonIds": [],
        "limitations": []
      }
    },
    {
      "schemaVersion": "1.0.0",
      "replayId": "replay_009",
      "entityKey": "controller:11255819",
      "entityIndex": 11255819,
      "serial": null,
      "handle": null,
      "classId": null,
      "className": null,
      "classification": "player_controller",
      "playerKey": "76561198080971309",
      "team": 3,
      "firstSeenTick": 320,
      "lastSeenTick": 138925,
      "independentValidation": {
        "categoryStatus": "not_required",
        "sampled": false,
        "visible": false,
        "identityStatus": "not_required",
        "timingStatus": "not_required",
        "comparisonIds": [],
        "limitations": []
      }
    },
    {
      "schemaVersion": "1.0.0",
      "replayId": "replay_009",
      "entityKey": "pawn:16302165",
      "entityIndex": 16302165,
      "serial": null,
      "handle": null,
      "classId": null,
      "className": null,
      "classification": "player_pawn",
      "playerKey": "76561198080971309",
      "team": 3,
      "firstSeenTick": 320,
      "lastSeenTick": 138925,
      "independentValidation": {
        "categoryStatus": "not_required",
        "sampled": false,
        "visible": false,
        "identityStatus": "not_required",
        "timingStatus": "not_required",
        "comparisonIds": [],
        "limitations": []
      }
    },
    {
      "schemaVersion": "1.0.0",
      "replayId": "replay_009",
      "entityKey": "2972:515:8440732:147:61246",
      "entityIndex": 2972,
      "serial": 515,
      "handle": 8440732,
      "classId": 147,
      "className": "CCitadel_Ability_GoldenIdol",
      "classification": "spirit_urn_candidate",
      "playerKey": null,
      "team": null,
      "firstSeenTick": 61246,
      "lastSeenTick": 62942,
      "independentValidation": {
        "categoryStatus": "partially_supported",
        "sampled": true,
        "visible": true,
        "identityStatus": "identity_ambiguous",
        "timingStatus": "identity_ambiguous",
        "comparisonIds": [
          "comparison_016"
        ],
        "limitations": [
          "Candidate classes are not proven canonical Urn object."
        ]
      }
    },
    {
      "schemaVersion": "1.0.0",
      "replayId": "replay_009",
      "entityKey": "3095:188:3083287:147:99528",
      "entityIndex": 3095,
      "serial": 188,
      "handle": 3083287,
      "classId": 147,
      "className": "CCitadel_Ability_GoldenIdol",
      "classification": "spirit_urn_candidate",
      "playerKey": null,
      "team": null,
      "firstSeenTick": 99528,
      "lastSeenTick": 101210,
      "independentValidation": {
        "categoryStatus": "partially_supported",
        "sampled": true,
        "visible": true,
        "identityStatus": "identity_ambiguous",
        "timingStatus": "identity_ambiguous",
        "comparisonIds": [
          "comparison_022"
        ],
        "limitations": [
          "Candidate classes are not proven canonical Urn object."
        ]
      }
    },
    {
      "schemaVersion": "1.0.0",
      "replayId": "replay_009",
      "entityKey": "3160:624:10226776:147:71997",
      "entityIndex": 3160,
      "serial": 624,
      "handle": 10226776,
      "classId": 147,
      "className": "CCitadel_Ability_GoldenIdol",
      "classification": "spirit_urn_candidate",
      "playerKey": null,
      "team": null,
      "firstSeenTick": 71997,
      "lastSeenTick": 72149,
      "independentValidation": {
        "categoryStatus": "partially_supported",
        "sampled": true,
        "visible": true,
        "identityStatus": "identity_ambiguous",
        "timingStatus": "identity_ambiguous",
        "comparisonIds": [
          "comparison_018"
        ],
        "limitations": [
          "Candidate classes are not proven canonical Urn object."
        ]
      }
    },
    {
      "schemaVersion": "1.0.0",
      "replayId": "replay_009",
      "entityKey": "3167:23:379999:147:70438",
      "entityIndex": 3167,
      "serial": 23,
      "handle": 379999,
      "classId": 147,
      "className": "CCitadel_Ability_GoldenIdol",
      "classification": "spirit_urn_candidate",
      "playerKey": null,
      "team": null,
      "firstSeenTick": 70438,
      "lastSeenTick": 71912,
      "independentValidation": {
        "categoryStatus": "partially_supported",
        "sampled": true,
        "visible": true,
        "identityStatus": "identity_ambiguous",
        "timingStatus": "identity_ambiguous",
        "comparisonIds": [
          "comparison_017"
        ],
        "limitations": [
          "Candidate classes are not proven canonical Urn object."
        ]
      }
    },
    {
      "schemaVersion": "1.0.0",
      "replayId": "replay_009",
      "entityKey": "3499:659:10800555:147:119603",
      "entityIndex": 3499,
      "serial": 659,
      "handle": 10800555,
      "classId": 147,
      "className": "CCitadel_Ability_GoldenIdol",
      "classification": "spirit_urn_candidate",
      "playerKey": null,
      "team": null,
      "firstSeenTick": 119603,
      "lastSeenTick": 120903,
      "independentValidation": {
        "categoryStatus": "partially_supported",
        "sampled": true,
        "visible": true,
        "identityStatus": "identity_ambiguous",
        "timingStatus": "identity_ambiguous",
        "comparisonIds": [
          "comparison_029"
        ],
        "limitations": [
          "Candidate classes are not proven canonical Urn object."
        ]
      }
    },
    {
      "schemaVersion": "1.0.0",
      "replayId": "replay_009",
      "entityKey": "420:507:8307108:447:-1",
      "entityIndex": 420,
      "serial": 507,
      "handle": 8307108,
      "classId": 447,
      "className": "CCitadel_HeroTestOrbSpawner",
      "classification": "spirit_urn_candidate",
      "playerKey": null,
      "team": null,
      "firstSeenTick": -1,
      "lastSeenTick": null,
      "independentValidation": {
        "categoryStatus": "partially_supported",
        "sampled": false,
        "visible": false,
        "identityStatus": "identity_ambiguous",
        "timingStatus": "identity_ambiguous",
        "comparisonIds": [],
        "limitations": [
          "Candidate classes are not proven canonical Urn object."
        ]
      }
    },
    {
      "schemaVersion": "1.0.0",
      "replayId": "replay_009",
      "entityKey": "428:85:1393068:447:-1",
      "entityIndex": 428,
      "serial": 85,
      "handle": 1393068,
      "classId": 447,
      "className": "CCitadel_HeroTestOrbSpawner",
      "classification": "spirit_urn_candidate",
      "playerKey": null,
      "team": null,
      "firstSeenTick": -1,
      "lastSeenTick": null,
      "independentValidation": {
        "categoryStatus": "partially_supported",
        "sampled": false,
        "visible": false,
        "identityStatus": "identity_ambiguous",
        "timingStatus": "identity_ambiguous",
        "comparisonIds": [],
        "limitations": [
          "Candidate classes are not proven canonical Urn object."
        ]
      }
    },
    {
      "schemaVersion": "1.0.0",
      "replayId": "replay_009",
      "entityKey": "3244:161:2641068:453:101210",
      "entityIndex": 3244,
      "serial": 161,
      "handle": 2641068,
      "classId": 453,
      "className": "CCitadel_IdolCashIn",
      "classification": "spirit_urn_candidate",
      "playerKey": null,
      "team": null,
      "firstSeenTick": 101210,
      "lastSeenTick": 102377,
      "independentValidation": {
        "categoryStatus": "partially_supported",
        "sampled": false,
        "visible": false,
        "identityStatus": "identity_ambiguous",
        "timingStatus": "identity_ambiguous",
        "comparisonIds": [],
        "limitations": [
          "Candidate classes are not proven canonical Urn object."
        ]
      }
    },
    {
      "schemaVersion": "1.0.0",
      "replayId": "replay_009",
      "entityKey": "3246:868:14224558:453:72149",
      "entityIndex": 3246,
      "serial": 868,
      "handle": 14224558,
      "classId": 453,
      "className": "CCitadel_IdolCashIn",
      "classification": "spirit_urn_candidate",
      "playerKey": null,
      "team": null,
      "firstSeenTick": 72149,
      "lastSeenTick": 73633,
      "independentValidation": {
        "categoryStatus": "partially_supported",
        "sampled": false,
        "visible": false,
        "identityStatus": "identity_ambiguous",
        "timingStatus": "identity_ambiguous",
        "comparisonIds": [],
        "limitations": [
          "Candidate classes are not proven canonical Urn object."
        ]
      }
    },
    {
      "schemaVersion": "1.0.0",
      "replayId": "replay_009",
      "entityKey": "3483:403:6606235:453:62942",
      "entityIndex": 3483,
      "serial": 403,
      "handle": 6606235,
      "classId": 453,
      "className": "CCitadel_IdolCashIn",
      "classification": "spirit_urn_candidate",
      "playerKey": null,
      "team": null,
      "firstSeenTick": 62942,
      "lastSeenTick": 64010,
      "independentValidation": {
        "categoryStatus": "partially_supported",
        "sampled": false,
        "visible": false,
        "identityStatus": "identity_ambiguous",
        "timingStatus": "identity_ambiguous",
        "comparisonIds": [],
        "limitations": [
          "Candidate classes are not proven canonical Urn object."
        ]
      }
    },
    {
      "schemaVersion": "1.0.0",
      "replayId": "replay_009",
      "entityKey": "3544:719:11783640:453:120903",
      "entityIndex": 3544,
      "serial": 719,
      "handle": 11783640,
      "classId": 453,
      "className": "CCitadel_IdolCashIn",
      "classification": "spirit_urn_candidate",
      "playerKey": null,
      "team": null,
      "firstSeenTick": 120903,
      "lastSeenTick": 122055,
      "independentValidation": {
        "categoryStatus": "partially_supported",
        "sampled": false,
        "visible": false,
        "identityStatus": "identity_ambiguous",
        "timingStatus": "identity_ambiguous",
        "comparisonIds": [],
        "limitations": [
          "Candidate classes are not proven canonical Urn object."
        ]
      }
    },
    {
      "schemaVersion": "1.0.0",
      "replayId": "replay_009",
      "entityKey": "403:21:344467:513:-1",
      "entityIndex": 403,
      "serial": 21,
      "handle": 344467,
      "classId": 513,
      "className": "CCitadel_PickupItemSpawner",
      "classification": "spirit_urn_candidate",
      "playerKey": null,
      "team": null,
      "firstSeenTick": -1,
      "lastSeenTick": null,
      "independentValidation": {
        "categoryStatus": "partially_supported",
        "sampled": false,
        "visible": false,
        "identityStatus": "identity_ambiguous",
        "timingStatus": "identity_ambiguous",
        "comparisonIds": [],
        "limitations": [
          "Candidate classes are not proven canonical Urn object."
        ]
      }
    },
    {
      "schemaVersion": "1.0.0",
      "replayId": "replay_009",
      "entityKey": "404:612:10027412:513:-1",
      "entityIndex": 404,
      "serial": 612,
      "handle": 10027412,
      "classId": 513,
      "className": "CCitadel_PickupItemSpawner",
      "classification": "spirit_urn_candidate",
      "playerKey": null,
      "team": null,
      "firstSeenTick": -1,
      "lastSeenTick": null,
      "independentValidation": {
        "categoryStatus": "partially_supported",
        "sampled": false,
        "visible": false,
        "identityStatus": "identity_ambiguous",
        "timingStatus": "identity_ambiguous",
        "comparisonIds": [],
        "limitations": [
          "Candidate classes are not proven canonical Urn object."
        ]
      }
    },
    {
      "schemaVersion": "1.0.0",
      "replayId": "replay_009",
      "entityKey": "495:284:4653551:608:-1",
      "entityIndex": 495,
      "serial": 284,
      "handle": 4653551,
      "classId": 608,
      "className": "CCitadelIdolReturnTrigger",
      "classification": "spirit_urn_candidate",
      "playerKey": null,
      "team": null,
      "firstSeenTick": -1,
      "lastSeenTick": null,
      "independentValidation": {
        "categoryStatus": "partially_supported",
        "sampled": false,
        "visible": false,
        "identityStatus": "identity_ambiguous",
        "timingStatus": "identity_ambiguous",
        "comparisonIds": [],
        "limitations": [
          "Candidate classes are not proven canonical Urn object."
        ]
      }
    },
    {
      "schemaVersion": "1.0.0",
      "replayId": "replay_009",
      "entityKey": "496:594:9732592:608:-1",
      "entityIndex": 496,
      "serial": 594,
      "handle": 9732592,
      "classId": 608,
      "className": "CCitadelIdolReturnTrigger",
      "classification": "spirit_urn_candidate",
      "playerKey": null,
      "team": null,
      "firstSeenTick": -1,
      "lastSeenTick": null,
      "independentValidation": {
        "categoryStatus": "partially_supported",
        "sampled": false,
        "visible": false,
        "identityStatus": "identity_ambiguous",
        "timingStatus": "identity_ambiguous",
        "comparisonIds": [],
        "limitations": [
          "Candidate classes are not proven canonical Urn object."
        ]
      }
    },
    {
      "schemaVersion": "1.0.0",
      "replayId": "replay_009",
      "entityKey": "3111:893:14634023:610:46080",
      "entityIndex": 3111,
      "serial": 893,
      "handle": 14634023,
      "classId": 610,
      "className": "CCitadelItemPickupIdol",
      "classification": "spirit_urn_candidate",
      "playerKey": null,
      "team": null,
      "firstSeenTick": 46080,
      "lastSeenTick": 61246,
      "independentValidation": {
        "categoryStatus": "partially_supported",
        "sampled": false,
        "visible": false,
        "identityStatus": "identity_ambiguous",
        "timingStatus": "identity_ambiguous",
        "comparisonIds": [],
        "limitations": [
          "Candidate classes are not proven canonical Urn object."
        ]
      }
    },
    {
      "schemaVersion": "1.0.0",
      "replayId": "replay_009",
      "entityKey": "3138:805:13192258:610:92160",
      "entityIndex": 3138,
      "serial": 805,
      "handle": 13192258,
      "classId": 610,
      "className": "CCitadelItemPickupIdol",
      "classification": "spirit_urn_candidate",
      "playerKey": null,
      "team": null,
      "firstSeenTick": 92160,
      "lastSeenTick": 99528,
      "independentValidation": {
        "categoryStatus": "partially_supported",
        "sampled": false,
        "visible": false,
        "identityStatus": "identity_ambiguous",
        "timingStatus": "identity_ambiguous",
        "comparisonIds": [],
        "limitations": [
          "Candidate classes are not proven canonical Urn object."
        ]
      }
    },
    {
      "schemaVersion": "1.0.0",
      "replayId": "replay_009",
      "entityKey": "3163:739:12110939:610:69120",
      "entityIndex": 3163,
      "serial": 739,
      "handle": 12110939,
      "classId": 610,
      "className": "CCitadelItemPickupIdol",
      "classification": "spirit_urn_candidate",
      "playerKey": null,
      "team": null,
      "firstSeenTick": 69120,
      "lastSeenTick": 70438,
      "independentValidation": {
        "categoryStatus": "partially_supported",
        "sampled": false,
        "visible": false,
        "identityStatus": "identity_ambiguous",
        "timingStatus": "identity_ambiguous",
        "comparisonIds": [],
        "limitations": [
          "Candidate classes are not proven canonical Urn object."
        ]
      }
    },
    {
      "schemaVersion": "1.0.0",
      "replayId": "replay_009",
      "entityKey": "3264:119:1952960:610:115200",
      "entityIndex": 3264,
      "serial": 119,
      "handle": 1952960,
      "classId": 610,
      "className": "CCitadelItemPickupIdol",
      "classification": "spirit_urn_candidate",
      "playerKey": null,
      "team": null,
      "firstSeenTick": 115200,
      "lastSeenTick": 119603,
      "independentValidation": {
        "categoryStatus": "partially_supported",
        "sampled": false,
        "visible": false,
        "identityStatus": "identity_ambiguous",
        "timingStatus": "identity_ambiguous",
        "comparisonIds": [],
        "limitations": [
          "Candidate classes are not proven canonical Urn object."
        ]
      }
    },
    {
      "schemaVersion": "1.0.0",
      "replayId": "replay_009",
      "entityKey": "3463:49:806279:610:71912",
      "entityIndex": 3463,
      "serial": 49,
      "handle": 806279,
      "classId": 610,
      "className": "CCitadelItemPickupIdol",
      "classification": "spirit_urn_candidate",
      "playerKey": null,
      "team": null,
      "firstSeenTick": 71912,
      "lastSeenTick": 71997,
      "independentValidation": {
        "categoryStatus": "partially_supported",
        "sampled": false,
        "visible": false,
        "identityStatus": "identity_ambiguous",
        "timingStatus": "identity_ambiguous",
        "comparisonIds": [],
        "limitations": [
          "Candidate classes are not proven canonical Urn object."
        ]
      }
    },
    {
      "schemaVersion": "1.0.0",
      "replayId": "replay_009",
      "entityKey": "348:356:5833052:711:-1",
      "entityIndex": 348,
      "serial": 356,
      "handle": 5833052,
      "classId": 711,
      "className": "CNPC_BarrackBoss",
      "classification": "barrack_boss_candidate",
      "playerKey": null,
      "team": null,
      "firstSeenTick": -1,
      "lastSeenTick": 132093,
      "independentValidation": {
        "categoryStatus": "partially_supported",
        "sampled": true,
        "visible": true,
        "identityStatus": "visual_identity_ambiguous",
        "timingStatus": "identity_ambiguous",
        "comparisonIds": [
          "comparison_033"
        ],
        "limitations": [
          "Base-area objects are visible, but CNPC_BarrackBoss mapping is not independently separated."
        ]
      }
    },
    {
      "schemaVersion": "1.0.0",
      "replayId": "replay_009",
      "entityKey": "349:122:1999197:711:-1",
      "entityIndex": 349,
      "serial": 122,
      "handle": 1999197,
      "classId": 711,
      "className": "CNPC_BarrackBoss",
      "classification": "barrack_boss_candidate",
      "playerKey": null,
      "team": null,
      "firstSeenTick": -1,
      "lastSeenTick": 131666,
      "independentValidation": {
        "categoryStatus": "partially_supported",
        "sampled": true,
        "visible": true,
        "identityStatus": "visual_identity_ambiguous",
        "timingStatus": "identity_ambiguous",
        "comparisonIds": [
          "comparison_032"
        ],
        "limitations": [
          "Base-area objects are visible, but CNPC_BarrackBoss mapping is not independently separated."
        ]
      }
    },
    {
      "schemaVersion": "1.0.0",
      "replayId": "replay_009",
      "entityKey": "350:567:9290078:711:-1",
      "entityIndex": 350,
      "serial": 567,
      "handle": 9290078,
      "classId": 711,
      "className": "CNPC_BarrackBoss",
      "classification": "barrack_boss_candidate",
      "playerKey": null,
      "team": null,
      "firstSeenTick": -1,
      "lastSeenTick": 104679,
      "independentValidation": {
        "categoryStatus": "partially_supported",
        "sampled": true,
        "visible": true,
        "identityStatus": "visual_identity_ambiguous",
        "timingStatus": "identity_ambiguous",
        "comparisonIds": [
          "comparison_025"
        ],
        "limitations": [
          "Base-area objects are visible, but CNPC_BarrackBoss mapping is not independently separated."
        ]
      }
    },
    {
      "schemaVersion": "1.0.0",
      "replayId": "replay_009",
      "entityKey": "351:568:9306463:711:-1",
      "entityIndex": 351,
      "serial": 568,
      "handle": 9306463,
      "classId": 711,
      "className": "CNPC_BarrackBoss",
      "classification": "barrack_boss_candidate",
      "playerKey": null,
      "team": null,
      "firstSeenTick": -1,
      "lastSeenTick": 104526,
      "independentValidation": {
        "categoryStatus": "partially_supported",
        "sampled": true,
        "visible": true,
        "identityStatus": "visual_identity_ambiguous",
        "timingStatus": "identity_ambiguous",
        "comparisonIds": [
          "comparison_023"
        ],
        "limitations": [
          "Base-area objects are visible, but CNPC_BarrackBoss mapping is not independently separated."
        ]
      }
    },
    {
      "schemaVersion": "1.0.0",
      "replayId": "replay_009",
      "entityKey": "352:39:639328:711:-1",
      "entityIndex": 352,
      "serial": 39,
      "handle": 639328,
      "classId": 711,
      "className": "CNPC_BarrackBoss",
      "classification": "barrack_boss_candidate",
      "playerKey": null,
      "team": null,
      "firstSeenTick": -1,
      "lastSeenTick": 108438,
      "independentValidation": {
        "categoryStatus": "partially_supported",
        "sampled": true,
        "visible": true,
        "identityStatus": "visual_identity_ambiguous",
        "timingStatus": "identity_ambiguous",
        "comparisonIds": [
          "comparison_027"
        ],
        "limitations": [
          "Base-area objects are visible, but CNPC_BarrackBoss mapping is not independently separated."
        ]
      }
    },
    {
      "schemaVersion": "1.0.0",
      "replayId": "replay_009",
      "entityKey": "353:150:2457953:711:-1",
      "entityIndex": 353,
      "serial": 150,
      "handle": 2457953,
      "classId": 711,
      "className": "CNPC_BarrackBoss",
      "classification": "barrack_boss_candidate",
      "playerKey": null,
      "team": null,
      "firstSeenTick": -1,
      "lastSeenTick": 108270,
      "independentValidation": {
        "categoryStatus": "partially_supported",
        "sampled": true,
        "visible": true,
        "identityStatus": "visual_identity_ambiguous",
        "timingStatus": "identity_ambiguous",
        "comparisonIds": [
          "comparison_026"
        ],
        "limitations": [
          "Base-area objects are visible, but CNPC_BarrackBoss mapping is not independently separated."
        ]
      }
    },
    {
      "schemaVersion": "1.0.0",
      "replayId": "replay_009",
      "entityKey": "354:185:3031394:711:-1",
      "entityIndex": 354,
      "serial": 185,
      "handle": 3031394,
      "classId": 711,
      "className": "CNPC_BarrackBoss",
      "classification": "barrack_boss_candidate",
      "playerKey": null,
      "team": null,
      "firstSeenTick": -1,
      "lastSeenTick": null,
      "independentValidation": {
        "categoryStatus": "partially_supported",
        "sampled": true,
        "visible": true,
        "identityStatus": "visual_identity_ambiguous",
        "timingStatus": "identity_ambiguous",
        "comparisonIds": [
          "comparison_006"
        ],
        "limitations": [
          "Base-area objects are visible, but CNPC_BarrackBoss mapping is not independently separated."
        ]
      }
    },
    {
      "schemaVersion": "1.0.0",
      "replayId": "replay_009",
      "entityKey": "355:262:4292963:711:-1",
      "entityIndex": 355,
      "serial": 262,
      "handle": 4292963,
      "classId": 711,
      "className": "CNPC_BarrackBoss",
      "classification": "barrack_boss_candidate",
      "playerKey": null,
      "team": null,
      "firstSeenTick": -1,
      "lastSeenTick": null,
      "independentValidation": {
        "categoryStatus": "partially_supported",
        "sampled": false,
        "visible": false,
        "identityStatus": "visual_identity_ambiguous",
        "timingStatus": "identity_ambiguous",
        "comparisonIds": [],
        "limitations": [
          "Base-area objects are visible, but CNPC_BarrackBoss mapping is not independently separated."
        ]
      }
    },
    {
      "schemaVersion": "1.0.0",
      "replayId": "replay_009",
      "entityKey": "356:30:491876:711:-1",
      "entityIndex": 356,
      "serial": 30,
      "handle": 491876,
      "classId": 711,
      "className": "CNPC_BarrackBoss",
      "classification": "barrack_boss_candidate",
      "playerKey": null,
      "team": null,
      "firstSeenTick": -1,
      "lastSeenTick": null,
      "independentValidation": {
        "categoryStatus": "partially_supported",
        "sampled": false,
        "visible": false,
        "identityStatus": "visual_identity_ambiguous",
        "timingStatus": "identity_ambiguous",
        "comparisonIds": [],
        "limitations": [
          "Base-area objects are visible, but CNPC_BarrackBoss mapping is not independently separated."
        ]
      }
    },
    {
      "schemaVersion": "1.0.0",
      "replayId": "replay_009",
      "entityKey": "357:476:7799141:711:-1",
      "entityIndex": 357,
      "serial": 476,
      "handle": 7799141,
      "classId": 711,
      "className": "CNPC_BarrackBoss",
      "classification": "barrack_boss_candidate",
      "playerKey": null,
      "team": null,
      "firstSeenTick": -1,
      "lastSeenTick": null,
      "independentValidation": {
        "categoryStatus": "partially_supported",
        "sampled": false,
        "visible": false,
        "identityStatus": "visual_identity_ambiguous",
        "timingStatus": "identity_ambiguous",
        "comparisonIds": [],
        "limitations": [
          "Base-area objects are visible, but CNPC_BarrackBoss mapping is not independently separated."
        ]
      }
    },
    {
      "schemaVersion": "1.0.0",
      "replayId": "replay_009",
      "entityKey": "424:1022:16744872:711:-1",
      "entityIndex": 424,
      "serial": 1022,
      "handle": 16744872,
      "classId": 711,
      "className": "CNPC_BarrackBoss",
      "classification": "barrack_boss_candidate",
      "playerKey": null,
      "team": null,
      "firstSeenTick": -1,
      "lastSeenTick": null,
      "independentValidation": {
        "categoryStatus": "partially_supported",
        "sampled": false,
        "visible": false,
        "identityStatus": "visual_identity_ambiguous",
        "timingStatus": "identity_ambiguous",
        "comparisonIds": [],
        "limitations": [
          "Base-area objects are visible, but CNPC_BarrackBoss mapping is not independently separated."
        ]
      }
    },
    {
      "schemaVersion": "1.0.0",
      "replayId": "replay_009",
      "entityKey": "425:627:10273193:711:-1",
      "entityIndex": 425,
      "serial": 627,
      "handle": 10273193,
      "classId": 711,
      "className": "CNPC_BarrackBoss",
      "classification": "barrack_boss_candidate",
      "playerKey": null,
      "team": null,
      "firstSeenTick": -1,
      "lastSeenTick": null,
      "independentValidation": {
        "categoryStatus": "partially_supported",
        "sampled": false,
        "visible": false,
        "identityStatus": "visual_identity_ambiguous",
        "timingStatus": "identity_ambiguous",
        "comparisonIds": [],
        "limitations": [
          "Base-area objects are visible, but CNPC_BarrackBoss mapping is not independently separated."
        ]
      }
    },
    {
      "schemaVersion": "1.0.0",
      "replayId": "replay_009",
      "entityKey": "419:614:10060195:712:-1",
      "entityIndex": 419,
      "serial": 614,
      "handle": 10060195,
      "classId": 712,
      "className": "CNPC_BaseDefenseSentry",
      "classification": "guardian",
      "playerKey": null,
      "team": null,
      "firstSeenTick": -1,
      "lastSeenTick": null,
      "independentValidation": {
        "categoryStatus": "not_observable",
        "sampled": true,
        "visible": false,
        "identityStatus": "not_visible",
        "timingStatus": "not_observable",
        "comparisonIds": [
          "comparison_034"
        ],
        "limitations": [
          "Camera did not clearly cover sampled Guardian entities."
        ]
      }
    },
    {
      "schemaVersion": "1.0.0",
      "replayId": "replay_009",
      "entityKey": "426:151:2474410:712:-1",
      "entityIndex": 426,
      "serial": 151,
      "handle": 2474410,
      "classId": 712,
      "className": "CNPC_BaseDefenseSentry",
      "classification": "guardian",
      "playerKey": null,
      "team": null,
      "firstSeenTick": -1,
      "lastSeenTick": null,
      "independentValidation": {
        "categoryStatus": "not_observable",
        "sampled": true,
        "visible": false,
        "identityStatus": "not_visible",
        "timingStatus": "not_observable",
        "comparisonIds": [
          "comparison_037"
        ],
        "limitations": [
          "Camera did not clearly cover sampled Guardian entities."
        ]
      }
    },
    {
      "schemaVersion": "1.0.0",
      "replayId": "replay_009",
      "entityKey": "427:910:14909867:712:-1",
      "entityIndex": 427,
      "serial": 910,
      "handle": 14909867,
      "classId": 712,
      "className": "CNPC_BaseDefenseSentry",
      "classification": "guardian",
      "playerKey": null,
      "team": null,
      "firstSeenTick": -1,
      "lastSeenTick": null,
      "independentValidation": {
        "categoryStatus": "not_observable",
        "sampled": false,
        "visible": false,
        "identityStatus": "not_visible",
        "timingStatus": "not_observable",
        "comparisonIds": [],
        "limitations": [
          "Camera did not clearly cover sampled Guardian entities."
        ]
      }
    },
    {
      "schemaVersion": "1.0.0",
      "replayId": "replay_009",
      "entityKey": "436:747:12239284:712:-1",
      "entityIndex": 436,
      "serial": 747,
      "handle": 12239284,
      "classId": 712,
      "className": "CNPC_BaseDefenseSentry",
      "classification": "guardian",
      "playerKey": null,
      "team": null,
      "firstSeenTick": -1,
      "lastSeenTick": null,
      "independentValidation": {
        "categoryStatus": "not_observable",
        "sampled": false,
        "visible": false,
        "identityStatus": "not_visible",
        "timingStatus": "not_observable",
        "comparisonIds": [],
        "limitations": [
          "Camera did not clearly cover sampled Guardian entities."
        ]
      }
    },
    {
      "schemaVersion": "1.0.0",
      "replayId": "replay_009",
      "entityKey": "477:820:13435357:712:-1",
      "entityIndex": 477,
      "serial": 820,
      "handle": 13435357,
      "classId": 712,
      "className": "CNPC_BaseDefenseSentry",
      "classification": "guardian",
      "playerKey": null,
      "team": null,
      "firstSeenTick": -1,
      "lastSeenTick": null,
      "independentValidation": {
        "categoryStatus": "not_observable",
        "sampled": false,
        "visible": false,
        "identityStatus": "not_visible",
        "timingStatus": "not_observable",
        "comparisonIds": [],
        "limitations": [
          "Camera did not clearly cover sampled Guardian entities."
        ]
      }
    },
    {
      "schemaVersion": "1.0.0",
      "replayId": "replay_009",
      "entityKey": "478:943:15450590:712:-1",
      "entityIndex": 478,
      "serial": 943,
      "handle": 15450590,
      "classId": 712,
      "className": "CNPC_BaseDefenseSentry",
      "classification": "guardian",
      "playerKey": null,
      "team": null,
      "firstSeenTick": -1,
      "lastSeenTick": null,
      "independentValidation": {
        "categoryStatus": "not_observable",
        "sampled": false,
        "visible": false,
        "identityStatus": "not_visible",
        "timingStatus": "not_observable",
        "comparisonIds": [],
        "limitations": [
          "Camera did not clearly cover sampled Guardian entities."
        ]
      }
    },
    {
      "schemaVersion": "1.0.0",
      "replayId": "replay_009",
      "entityKey": "479:66:1081823:712:-1",
      "entityIndex": 479,
      "serial": 66,
      "handle": 1081823,
      "classId": 712,
      "className": "CNPC_BaseDefenseSentry",
      "classification": "guardian",
      "playerKey": null,
      "team": null,
      "firstSeenTick": -1,
      "lastSeenTick": null,
      "independentValidation": {
        "categoryStatus": "not_observable",
        "sampled": true,
        "visible": false,
        "identityStatus": "not_visible",
        "timingStatus": "not_observable",
        "comparisonIds": [
          "comparison_035"
        ],
        "limitations": [
          "Camera did not clearly cover sampled Guardian entities."
        ]
      }
    },
    {
      "schemaVersion": "1.0.0",
      "replayId": "replay_009",
      "entityKey": "480:915:14991840:712:-1",
      "entityIndex": 480,
      "serial": 915,
      "handle": 14991840,
      "classId": 712,
      "className": "CNPC_BaseDefenseSentry",
      "classification": "guardian",
      "playerKey": null,
      "team": null,
      "firstSeenTick": -1,
      "lastSeenTick": null,
      "independentValidation": {
        "categoryStatus": "not_observable",
        "sampled": true,
        "visible": false,
        "identityStatus": "not_visible",
        "timingStatus": "not_observable",
        "comparisonIds": [
          "comparison_036"
        ],
        "limitations": [
          "Camera did not clearly cover sampled Guardian entities."
        ]
      }
    },
    {
      "schemaVersion": "1.0.0",
      "replayId": "replay_009",
      "entityKey": "307:381:6242611:713:-1",
      "entityIndex": 307,
      "serial": 381,
      "handle": 6242611,
      "classId": 713,
      "className": "CNPC_Boss_Tier2",
      "classification": "walker",
      "playerKey": null,
      "team": null,
      "firstSeenTick": -1,
      "lastSeenTick": 104528,
      "independentValidation": {
        "categoryStatus": "validated_with_constraints",
        "sampled": true,
        "visible": true,
        "identityStatus": "visual_identity_supported",
        "timingStatus": "partially_supported",
        "comparisonIds": [
          "comparison_005",
          "comparison_024"
        ],
        "limitations": [
          "Class identity is visually plausible for Walker-type objects, but deletion timing is mostly not visible."
        ]
      }
    },
    {
      "schemaVersion": "1.0.0",
      "replayId": "replay_009",
      "entityKey": "308:523:8569140:713:-1",
      "entityIndex": 308,
      "serial": 523,
      "handle": 8569140,
      "classId": 713,
      "className": "CNPC_Boss_Tier2",
      "classification": "walker",
      "playerKey": null,
      "team": null,
      "firstSeenTick": -1,
      "lastSeenTick": null,
      "independentValidation": {
        "categoryStatus": "validated_with_constraints",
        "sampled": true,
        "visible": true,
        "identityStatus": "visual_identity_supported",
        "timingStatus": "partially_supported",
        "comparisonIds": [
          "comparison_007"
        ],
        "limitations": [
          "Class identity is visually plausible for Walker-type objects, but deletion timing is mostly not visible."
        ]
      }
    },
    {
      "schemaVersion": "1.0.0",
      "replayId": "replay_009",
      "entityKey": "309:685:11223349:713:-1",
      "entityIndex": 309,
      "serial": 685,
      "handle": 11223349,
      "classId": 713,
      "className": "CNPC_Boss_Tier2",
      "classification": "walker",
      "playerKey": null,
      "team": null,
      "firstSeenTick": -1,
      "lastSeenTick": 86132,
      "independentValidation": {
        "categoryStatus": "validated_with_constraints",
        "sampled": true,
        "visible": true,
        "identityStatus": "visual_identity_supported",
        "timingStatus": "partially_supported",
        "comparisonIds": [
          "comparison_009",
          "comparison_019"
        ],
        "limitations": [
          "Class identity is visually plausible for Walker-type objects, but deletion timing is mostly not visible."
        ]
      }
    },
    {
      "schemaVersion": "1.0.0",
      "replayId": "replay_009",
      "entityKey": "310:1003:16433462:713:-1",
      "entityIndex": 310,
      "serial": 1003,
      "handle": 16433462,
      "classId": 713,
      "className": "CNPC_Boss_Tier2",
      "classification": "walker",
      "playerKey": null,
      "team": null,
      "firstSeenTick": -1,
      "lastSeenTick": 113143,
      "independentValidation": {
        "categoryStatus": "validated_with_constraints",
        "sampled": true,
        "visible": true,
        "identityStatus": "visual_identity_supported",
        "timingStatus": "partially_supported",
        "comparisonIds": [
          "comparison_003",
          "comparison_028"
        ],
        "limitations": [
          "Class identity is visually plausible for Walker-type objects, but deletion timing is mostly not visible."
        ]
      }
    },
    {
      "schemaVersion": "1.0.0",
      "replayId": "replay_009",
      "entityKey": "311:565:9257271:713:-1",
      "entityIndex": 311,
      "serial": 565,
      "handle": 9257271,
      "classId": 713,
      "className": "CNPC_Boss_Tier2",
      "classification": "walker",
      "playerKey": null,
      "team": null,
      "firstSeenTick": -1,
      "lastSeenTick": 95814,
      "independentValidation": {
        "categoryStatus": "validated_with_constraints",
        "sampled": true,
        "visible": true,
        "identityStatus": "visual_identity_supported",
        "timingStatus": "partially_supported",
        "comparisonIds": [
          "comparison_004",
          "comparison_020"
        ],
        "limitations": [
          "Class identity is visually plausible for Walker-type objects, but deletion timing is mostly not visible."
        ]
      }
    },
    {
      "schemaVersion": "1.0.0",
      "replayId": "replay_009",
      "entityKey": "312:533:8732984:713:-1",
      "entityIndex": 312,
      "serial": 533,
      "handle": 8732984,
      "classId": 713,
      "className": "CNPC_Boss_Tier2",
      "classification": "walker",
      "playerKey": null,
      "team": null,
      "firstSeenTick": -1,
      "lastSeenTick": null,
      "independentValidation": {
        "categoryStatus": "validated_with_constraints",
        "sampled": true,
        "visible": true,
        "identityStatus": "visual_identity_supported",
        "timingStatus": "partially_supported",
        "comparisonIds": [
          "comparison_008"
        ],
        "limitations": [
          "Class identity is visually plausible for Walker-type objects, but deletion timing is mostly not visible."
        ]
      }
    },
    {
      "schemaVersion": "1.0.0",
      "replayId": "replay_009",
      "entityKey": "302:761:12468526:714:-1",
      "entityIndex": 302,
      "serial": 761,
      "handle": 12468526,
      "classId": 714,
      "className": "CNPC_Boss_Tier3",
      "classification": "boss_tier3_candidate",
      "playerKey": null,
      "team": null,
      "firstSeenTick": -1,
      "lastSeenTick": null,
      "independentValidation": {
        "categoryStatus": "partially_supported",
        "sampled": true,
        "visible": true,
        "identityStatus": "visual_identity_ambiguous",
        "timingStatus": "identity_ambiguous",
        "comparisonIds": [
          "comparison_002"
        ],
        "limitations": [
          "Patron/base phase visibility exists, but class-level identity remains ambiguous."
        ]
      }
    },
    {
      "schemaVersion": "1.0.0",
      "replayId": "replay_009",
      "entityKey": "303:242:3965231:714:-1",
      "entityIndex": 303,
      "serial": 242,
      "handle": 3965231,
      "classId": 714,
      "className": "CNPC_Boss_Tier3",
      "classification": "boss_tier3_candidate",
      "playerKey": null,
      "team": null,
      "firstSeenTick": -1,
      "lastSeenTick": null,
      "independentValidation": {
        "categoryStatus": "partially_supported",
        "sampled": false,
        "visible": false,
        "identityStatus": "visual_identity_ambiguous",
        "timingStatus": "identity_ambiguous",
        "comparisonIds": [],
        "limitations": [
          "Patron/base phase visibility exists, but class-level identity remains ambiguous."
        ]
      }
    },
    {
      "schemaVersion": "1.0.0",
      "replayId": "replay_009",
      "entityKey": "2714:253:4147866:718:-1",
      "entityIndex": 2714,
      "serial": 253,
      "handle": 4147866,
      "classId": 718,
      "className": "CNPC_MidBoss",
      "classification": "mid_boss",
      "playerKey": null,
      "team": null,
      "firstSeenTick": -1,
      "lastSeenTick": 97066,
      "independentValidation": {
        "categoryStatus": "validated_with_constraints",
        "sampled": true,
        "visible": true,
        "identityStatus": "visual_identity_supported",
        "timingStatus": "validated_with_constraints",
        "comparisonIds": [
          "comparison_001",
          "comparison_021"
        ],
        "limitations": [
          "Deletion is not promoted to kill or reward."
        ]
      }
    },
    {
      "schemaVersion": "1.0.0",
      "replayId": "replay_009",
      "entityKey": "3289:380:6229209:718:123857",
      "entityIndex": 3289,
      "serial": 380,
      "handle": 6229209,
      "classId": 718,
      "className": "CNPC_MidBoss",
      "classification": "mid_boss",
      "playerKey": null,
      "team": null,
      "firstSeenTick": 123857,
      "lastSeenTick": 126707,
      "independentValidation": {
        "categoryStatus": "validated_with_constraints",
        "sampled": true,
        "visible": true,
        "identityStatus": "visual_identity_supported",
        "timingStatus": "validated_with_constraints",
        "comparisonIds": [
          "comparison_030",
          "comparison_031"
        ],
        "limitations": [
          "Deletion is not promoted to kill or reward."
        ]
      }
    },
    {
      "schemaVersion": "1.0.0",
      "replayId": "replay_009",
      "entityKey": "2519:801:13126103:735:-1",
      "entityIndex": 2519,
      "serial": 801,
      "handle": 13126103,
      "classId": 735,
      "className": "CNPC_TrooperBoss",
      "classification": "trooper_boss_candidate",
      "playerKey": null,
      "team": null,
      "firstSeenTick": -1,
      "lastSeenTick": 43122,
      "independentValidation": {
        "categoryStatus": "partially_supported",
        "sampled": true,
        "visible": true,
        "identityStatus": "visual_identity_ambiguous",
        "timingStatus": "identity_ambiguous",
        "comparisonIds": [
          "comparison_012"
        ],
        "limitations": [
          "TrooperBoss may be auxiliary; visual mapping unresolved."
        ]
      }
    },
    {
      "schemaVersion": "1.0.0",
      "replayId": "replay_009",
      "entityKey": "2520:242:3967448:735:-1",
      "entityIndex": 2520,
      "serial": 242,
      "handle": 3967448,
      "classId": 735,
      "className": "CNPC_TrooperBoss",
      "classification": "trooper_boss_candidate",
      "playerKey": null,
      "team": null,
      "firstSeenTick": -1,
      "lastSeenTick": 28942,
      "independentValidation": {
        "categoryStatus": "partially_supported",
        "sampled": true,
        "visible": true,
        "identityStatus": "visual_identity_ambiguous",
        "timingStatus": "identity_ambiguous",
        "comparisonIds": [
          "comparison_010"
        ],
        "limitations": [
          "TrooperBoss may be auxiliary; visual mapping unresolved."
        ]
      }
    },
    {
      "schemaVersion": "1.0.0",
      "replayId": "replay_009",
      "entityKey": "2521:565:9259481:735:-1",
      "entityIndex": 2521,
      "serial": 565,
      "handle": 9259481,
      "classId": 735,
      "className": "CNPC_TrooperBoss",
      "classification": "trooper_boss_candidate",
      "playerKey": null,
      "team": null,
      "firstSeenTick": -1,
      "lastSeenTick": 50287,
      "independentValidation": {
        "categoryStatus": "partially_supported",
        "sampled": true,
        "visible": true,
        "identityStatus": "visual_identity_ambiguous",
        "timingStatus": "identity_ambiguous",
        "comparisonIds": [
          "comparison_015"
        ],
        "limitations": [
          "TrooperBoss may be auxiliary; visual mapping unresolved."
        ]
      }
    },
    {
      "schemaVersion": "1.0.0",
      "replayId": "replay_009",
      "entityKey": "2522:764:12519898:735:-1",
      "entityIndex": 2522,
      "serial": 764,
      "handle": 12519898,
      "classId": 735,
      "className": "CNPC_TrooperBoss",
      "classification": "trooper_boss_candidate",
      "playerKey": null,
      "team": null,
      "firstSeenTick": -1,
      "lastSeenTick": 45640,
      "independentValidation": {
        "categoryStatus": "partially_supported",
        "sampled": true,
        "visible": true,
        "identityStatus": "visual_identity_ambiguous",
        "timingStatus": "identity_ambiguous",
        "comparisonIds": [
          "comparison_013"
        ],
        "limitations": [
          "TrooperBoss may be auxiliary; visual mapping unresolved."
        ]
      }
    },
    {
      "schemaVersion": "1.0.0",
      "replayId": "replay_009",
      "entityKey": "2523:122:2001371:735:-1",
      "entityIndex": 2523,
      "serial": 122,
      "handle": 2001371,
      "classId": 735,
      "className": "CNPC_TrooperBoss",
      "classification": "trooper_boss_candidate",
      "playerKey": null,
      "team": null,
      "firstSeenTick": -1,
      "lastSeenTick": 50014,
      "independentValidation": {
        "categoryStatus": "partially_supported",
        "sampled": true,
        "visible": true,
        "identityStatus": "visual_identity_ambiguous",
        "timingStatus": "identity_ambiguous",
        "comparisonIds": [
          "comparison_014"
        ],
        "limitations": [
          "TrooperBoss may be auxiliary; visual mapping unresolved."
        ]
      }
    },
    {
      "schemaVersion": "1.0.0",
      "replayId": "replay_009",
      "entityKey": "2524:866:14191068:735:-1",
      "entityIndex": 2524,
      "serial": 866,
      "handle": 14191068,
      "classId": 735,
      "className": "CNPC_TrooperBoss",
      "classification": "trooper_boss_candidate",
      "playerKey": null,
      "team": null,
      "firstSeenTick": -1,
      "lastSeenTick": 41449,
      "independentValidation": {
        "categoryStatus": "partially_supported",
        "sampled": true,
        "visible": true,
        "identityStatus": "visual_identity_ambiguous",
        "timingStatus": "identity_ambiguous",
        "comparisonIds": [
          "comparison_011"
        ],
        "limitations": [
          "TrooperBoss may be auxiliary; visual mapping unresolved."
        ]
      }
    }
  ]
}
