{
  "schemaVersion": 1,
  "replayId": "replay_009",
  "status": "unavailable",
  "objects": [
    {
      "objectType": "Spirit/Soul Urn",
      "geometrySource": null,
      "positionOrRegion": {},
      "mapVersionStatus": "unknown_map_version",
      "usableForDistance": false,
      "usableForRegionMembership": false,
      "confidence": "unknown",
      "limitations": [
        "No replay-009 static geometry validation."
      ]
    },
    {
      "objectType": "Urn deposit locations",
      "geometrySource": null,
      "positionOrRegion": {},
      "mapVersionStatus": "unknown_map_version",
      "usableForDistance": false,
      "usableForRegionMembership": false,
      "confidence": "unknown",
      "limitations": [
        "No replay-009 static geometry validation."
      ]
    },
    {
      "objectType": "Mid Boss",
      "geometrySource": null,
      "positionOrRegion": {},
      "mapVersionStatus": "unknown_map_version",
      "usableForDistance": false,
      "usableForRegionMembership": false,
      "confidence": "unknown",
      "limitations": [
        "No replay-009 static geometry validation."
      ]
    },
    {
      "objectType": "Guardians",
      "geometrySource": null,
      "positionOrRegion": {},
      "mapVersionStatus": "unknown_map_version",
      "usableForDistance": false,
      "usableForRegionMembership": false,
      "confidence": "unknown",
      "limitations": [
        "No replay-009 static geometry validation."
      ]
    },
    {
      "objectType": "Walkers",
      "geometrySource": null,
      "positionOrRegion": {},
      "mapVersionStatus": "unknown_map_version",
      "usableForDistance": false,
      "usableForRegionMembership": false,
      "confidence": "unknown",
      "limitations": [
        "No replay-009 static geometry validation."
      ]
    },
    {
      "objectType": "Patron/base structures",
      "geometrySource": null,
      "positionOrRegion": {},
      "mapVersionStatus": "unknown_map_version",
      "usableForDistance": false,
      "usableForRegionMembership": false,
      "confidence": "unknown",
      "limitations": [
        "No replay-009 static geometry validation."
      ]
    }
  ]
}
