{
  "schemaVersion": "1.0.0",
  "taskId": "072",
  "generatedBy": "tools/measure-replay-009-user-map-landmarks.mjs",
  "imagesFound": 8,
  "rolesClassified": {
    "derived_landmark_map": 1,
    "mechanic_spawn_diagram": 1,
    "replay_observed_standard_minimap": 1,
    "user_modded_minimap": 5
  },
  "standardReplayMinimapIdentified": true,
  "moddedMapsIdentified": 5,
  "derivedLandmarkMapIdentified": true,
  "urnDiagramIdentified": true,
  "landmarkMeasurements": 34,
  "midBossMeasurements": 2,
  "walkerMeasurements": 12,
  "guardianMeasurements": 6,
  "baseLandmarkMeasurements": 14,
  "crossImageRegistration": "same_underlying_geometry_with_crop_scale_limitations",
  "correspondenceCandidates": 2,
  "fitAnchorsPlanned": 5,
  "validationAnchorsReserved": 2,
  "rejectedLandmarkClasses": 3,
  "transformFitted": false,
  "lanesRegionsProximityEmitted": false,
  "mechanicEffectsApplied": 0,
  "gate": "replay_009_independent_landmark_coordinates_ready_with_limitations",
  "blockedTransformValidationContinuation": "tasks/blocked/073-retry-replay-009-transform-validation-with-measured-landmarks.md",
  "protections": {
    "replay005Read": false,
    "replay005Processed": false,
    "botFixturesProcessed": false,
    "userImagesCommitted": false
  }
}
